[{"FileName":"00689D31-8491-4643-B3C8-45241FBBD47C.hea","Timestamp":"2025-09-07 21:17:09","QRSMorph":"Normal","Onset":342,"QRSd":102,"QTd":420,"Comment":"Add any comments here. Observer comments will appear to the right of this box. >>>>>>>>>>>>>>>>>>>>>>>> -","I_P":"qRs","II_P":"qRs","III_P":"qR","aVR_P":"rSr'","aVL_P":"rS","aVF_P":"qR","V1_P":"rSr'","V2_P":"SR'","V3_P":"qRs","V4_P":"qR","V5_P":"qR","V6_P":"qR","I_N_S":"_","II_N_S":"_","III_N_S":"Notch","aVR_N_S":"_","aVL_N_S":"Notch","aVF_N_S":"_","V1_N_S":"_","V2_N_S":"_","V3_N_S":"_","V4_N_S":"_","V5_N_S":"_","V6_N_S":"_","I_N_Son":0,"II_N_Son":0,"III_N_Son":362,"aVR_N_Son":0,"aVL_N_Son":400,"aVF_N_Son":0,"V1_N_Son":0,"V2_N_Son":0,"V3_N_Son":0,"V4_N_Son":0,"V5_N_Son":0,"V6_N_Son":0,"I_N_Soff":0,"II_N_Soff":0,"III_N_Soff":380,"aVR_N_Soff":0,"aVL_N_Soff":414,"aVF_N_Soff":0,"V1_N_Soff":0,"V2_N_Soff":0,"V3_N_Soff":0,"V4_N_Soff":0,"V5_N_Soff":0,"V6_N_Soff":0,"I_R_Peak":0,"II_R_Peak":0,"III_R_Peak":0,"aVR_R_Peak":0,"aVL_R_Peak":0,"aVF_R_Peak":0,"V1_R_Peak":0,"V2_R_Peak":0,"V3_R_Peak":0,"V4_R_Peak":0,"V5_R_Peak":0,"V6_R_Peak":0,"Provenance":"/CM_V1.0<DrWho>Observer1|Observer2|-\\"},{"FileName":"00689D31-8491-4643-B3C8-45241FBBD47C.hea","Timestamp":"2025-09-07 21:29:13","QRSMorph":"Normal","Onset":344,"QRSd":102,"QTd":414,"Comment":"Add any comments here. Observer comments will appear to the right of this box. >>>>>>>>>>>>>>>>>>>>>>>> - -","I_P":"qRs","II_P":"qRs","III_P":"qR","aVR_P":"rSr'","aVL_P":"rS","aVF_P":"qR","V1_P":"rSr'","V2_P":"RS","V3_P":"qRs","V4_P":"qR","V5_P":"qR","V6_P":"qR","I_N_S":"_","II_N_S":"_","III_N_S":"Notch","aVR_N_S":"_","aVL_N_S":"Notch","aVF_N_S":"_","V1_N_S":"_","V2_N_S":"_","V3_N_S":"_","V4_N_S":"_","V5_N_S":"_","V6_N_S":"_","I_N_Son":0,"II_N_Son":0,"III_N_Son":0,"aVR_N_Son":0,"aVL_N_Son":398,"aVF_N_Son":0,"V1_N_Son":0,"V2_N_Son":0,"V3_N_Son":0,"V4_N_Son":0,"V5_N_Son":0,"V6_N_Son":0,"I_N_Soff":0,"II_N_Soff":0,"III_N_Soff":0,"aVR_N_Soff":0,"aVL_N_Soff":412,"aVF_N_Soff":0,"V1_N_Soff":0,"V2_N_Soff":0,"V3_N_Soff":0,"V4_N_Soff":0,"V5_N_Soff":0,"V6_N_Soff":0,"I_R_Peak":0,"II_R_Peak":0,"III_R_Peak":0,"aVR_R_Peak":0,"aVL_R_Peak":0,"aVF_R_Peak":0,"V1_R_Peak":0,"V2_R_Peak":0,"V3_R_Peak":0,"V4_R_Peak":0,"V5_R_Peak":0,"V6_R_Peak":0,"Provenance":"/CM_V1.0<DrWho>Observer1|Observer2|-\\"},{"FileName":"0B967A7E-3BF9-48E1-B159-D4B48982F94C.hea","Timestamp":"2025-09-15 15:53:04","QRSMorph":"Others","Onset":348,"QRSd":108,"QTd":356,"Comment":"-","I_P":"qRs","II_P":"qRs","III_P":"qR","aVR_P":"rSr'","aVL_P":"rS","aVF_P":"qRs","V1_P":"rSr'","V2_P":"RS","V3_P":"qRs","V4_P":"qRs","V5_P":"qR","V6_P":"qR","I_N_S":"_","II_N_S":"_","III_N_S":"Notch","aVR_N_S":"_","aVL_N_S":"_","aVF_N_S":"_","V1_N_S":"_","V2_N_S":"Notch","V3_N_S":"_","V4_N_S":"_","V5_N_S":"_","V6_N_S":"_","I_N_Son":0,"II_N_Son":0,"III_N_Son":368,"aVR_N_Son":0,"aVL_N_Son":366,"aVF_N_Son":0,"V1_N_Son":0,"V2_N_Son":392,"V3_N_Son":0,"V4_N_Son":0,"V5_N_Son":0,"V6_N_Son":0,"I_N_Soff":0,"II_N_Soff":0,"III_N_Soff":380,"aVR_N_Soff":0,"aVL_N_Soff":382,"aVF_N_Soff":0,"V1_N_Soff":0,"V2_N_Soff":402,"V3_N_Soff":0,"V4_N_Soff":0,"V5_N_Soff":0,"V6_N_Soff":0,"I_R_Peak":49,"II_R_Peak":0,"III_R_Peak":0,"aVR_R_Peak":0,"aVL_R_Peak":0,"aVF_R_Peak":0,"V1_R_Peak":0,"V2_R_Peak":45,"V3_R_Peak":0,"V4_R_Peak":0,"V5_R_Peak":0,"V6_R_Peak":0,"Provenance":"/CM_V1.0<DrWho>Observer1|Observer2|-\\"},{"FileName":"0CB6ED46-24E8-488A-A5F4-08950106C9CC.hea","Timestamp":"2025-09-15 15:56:22","QRSMorph":"RBBB-type","Onset":354,"QRSd":96,"QTd":384,"Comment":"-","I_P":"RS","II_P":"qRs","III_P":"qRs","aVR_P":"rSr'","aVL_P":"rS","aVF_P":"qRs","V1_P":"rSR's'","V2_P":"Rs","V3_P":"qRs","V4_P":"qRs","V5_P":"qRs","V6_P":"qRs","I_N_S":"_","II_N_S":"_","III_N_S":"_","aVR_N_S":"_","aVL_N_S":"_","aVF_N_S":"_","V1_N_S":"_","V2_N_S":"_","V3_N_S":"_","V4_N_S":"_","V5_N_S":"_","V6_N_S":"_","I_N_Son":0,"II_N_Son":0,"III_N_Son":0,"aVR_N_Son":0,"aVL_N_Son":0,"aVF_N_Son":0,"V1_N_Son":0,"V2_N_Son":0,"V3_N_Son":0,"V4_N_Son":0,"V5_N_Son":0,"V6_N_Son":0,"I_N_Soff":0,"II_N_Soff":0,"III_N_Soff":0,"aVR_N_Soff":0,"aVL_N_Soff":0,"aVF_N_Soff":0,"V1_N_Soff":0,"V2_N_Soff":0,"V3_N_Soff":0,"V4_N_Soff":0,"V5_N_Soff":0,"V6_N_Soff":0,"I_R_Peak":49,"II_R_Peak":0,"III_R_Peak":0,"aVR_R_Peak":0,"aVL_R_Peak":0,"aVF_R_Peak":0,"V1_R_Peak":66,"V2_R_Peak":41,"V3_R_Peak":0,"V4_R_Peak":0,"V5_R_Peak":0,"V6_R_Peak":0,"Provenance":"/CM_V1.0<DrWho>Observer1|Observer2|-\\"}]